tests/__init__.py
tests/test_jmeter_server.py
mseep_jmeter_mcp_server-0.1.2.dist-info/METADATA
mseep_jmeter_mcp_server-0.1.2.dist-info/WHEEL
mseep_jmeter_mcp_server-0.1.2.dist-info/top_level.txt
mseep_jmeter_mcp_server-0.1.2.dist-info/RECORD
