Metadata-Version: 2.4
Name: mseep-jmeter-mcp-server
Version: 0.1.2
Summary: JMeter MCP Server
Home-page: 
Author: mseep
Author-email: mseep <support@skydeck.ai>
Maintainer-email: mseep <support@skydeck.ai>
Requires-Python: >=3.6
Requires-Dist: httpx>=0.28.1
Requires-Dist: mcp[cli]>=1.6.0
Dynamic: author
Dynamic: requires-python
